{
    "words": [
        {"id": 1, "word": "FIBRE" },
        {"id": 2, "word": "WENCH" },
        {"id": 3, "word": "CIGAR" },
        {"id": 4, "word": "REBUT" },
        {"id": 5, "word": "AWAKE" },
        {"id": 6, "word": "BLUSH" },
        {"id": 7, "word": "FOCAL" },
        {"id": 8, "word": "EVADE" },
        {"id": 9, "word": "SERVE" },
        {"id": 10, "word": "KARMA" },
        {"id": 11, "word": "QUIET" },
        {"id": 12, "word": "REACT" },
        {"id": 13, "word": "CROAK" },
        {"id": 14, "word": "HELIX" },
        {"id": 15, "word": "TRAWL" },
        {"id": 16, "word": "DIGIT" },
        {"id": 17, "word": "LINEN" },
        {"id": 18, "word": "PRINT" },
        {"id": 19, "word": "PARRY" },
        {"id": 20, "word": "ROGUE" }
    ],

    "letters": [
        {"key": "A"},
        {"key": "B"},
        {"key": "C"},
        {"key": "D"},
        {"key": "E"},
        {"key": "F"},
        {"key": "G"},
        {"key": "H"},
        {"key": "I"},
        {"key": "J"},
        {"key": "K"},
        {"key": "L"},
        {"key": "M"},
        {"key": "N"},
        {"key": "O"},
        {"key": "P"},
        {"key": "Q"},
        {"key": "R"},
        {"key": "S"},
        {"key": "T"},
        {"key": "U"},
        {"key": "V"},
        {"key": "W"},
        {"key": "X"},
        {"key": "Y"},
        {"key": "Z"}
    ]
}